mappy_rs-0.0.7.dist-info/METADATA
mappy_rs-0.0.7.dist-info/WHEEL
mappy_rs-0.0.7.dist-info/license_files/LICENSE.MD
mappy_rs/__init__.py
mappy_rs/mappy_rs.cpython-39-darwin.so
mappy_rs-0.0.7.dist-info/RECORD
