Metadata-Version: 2.3
Name: mappy-rs
Version: 0.0.7
Classifier: Programming Language :: Rust
Classifier: Programming Language :: Python :: Implementation :: CPython
Classifier: Programming Language :: Python :: Implementation :: PyPy
Classifier: Intended Audience :: Science/Research
Classifier: Programming Language :: Python :: 3.8
Classifier: Programming Language :: Python :: 3.9
Classifier: Programming Language :: Python :: 3.10
Classifier: Programming Language :: Python :: 3.11
Requires-Dist: pytest ; extra == 'tests'
Requires-Dist: mappy-rs[tests] ; extra == 'dev'
Requires-Dist: pre-commit ; extra == 'dev'
Requires-Dist: mappy-rs[dev] ; extra == 'benchmark'
Requires-Dist: pytest-benchmark[histogram] ; extra == 'benchmark'
Requires-Dist: mappy ; extra == 'benchmark'
Provides-Extra: tests
Provides-Extra: dev
Provides-Extra: benchmark
License-File: LICENSE.MD
Summary: A multithreaded python wrapper for rust bindings of minimap2.
Keywords: alignment,bioinformatics,python,rust,minimap2
Author: Rory Munro <roryjmunro1@gmail.com>
Author-email: Rory Munro <rory.munro@nottingham.ac.uk>, Alexander Payne <alexander.payne@nottingham.ac.uk>
Maintainer-email: Rory Munro <rory.munro@nottingham.ac.uk>
License: BSD 3-Clause License
Requires-Python: >=3.8
Project-URL: Source Code, https://github.com/adoni5/mappy-rs
